{"expireTime":9007200844326220000,"key":"transformer-remark-markdown-html-ast-2c3a4c68714d00f499b5753c648afa85-gatsby-remark-prismjsgatsby-remark-katex-","val":{"type":"root","children":[{"type":"element","tagName":"h1","properties":{},"children":[{"type":"text","value":"Hackers Against Dumb Posts","position":{"start":{"line":2,"column":3,"offset":3},"end":{"line":2,"column":29,"offset":29}}}],"position":{"start":{"line":2,"column":1,"offset":1},"end":{"line":2,"column":29,"offset":29}}},{"type":"text","value":"\n"},{"type":"raw","value":"<img class=\"align-self-center mr-3\" src=\"/img/HADP Logo\" width=\"120\" height=\"120\" alt=\"HADP Logo\">","position":{"start":{"line":4,"column":1,"offset":31},"end":{"line":4,"column":99,"offset":129}}},{"type":"text","value":"\n"},{"type":"element","tagName":"p","properties":{},"children":[{"type":"text","value":"We are all familiar with the incident of the twitter NASA girl who lost her internship due to vulgar and inappropriate tweets: ","position":{"start":{"line":6,"column":1,"offset":131},"end":{"line":6,"column":128,"offset":258}}},{"type":"raw","value":"<a href=\"https://i.dailymail.co.uk/i/newpix/2018/08/23/10/4F5352F900000578-6090055-image-m-9_1535017175115.jpg\">","position":{"start":{"line":6,"column":128,"offset":258},"end":{"line":6,"column":240,"offset":370}}},{"type":"text","value":"an example of a dumb post","position":{"start":{"line":6,"column":240,"offset":370},"end":{"line":6,"column":265,"offset":395}}},{"type":"raw","value":"</a>","position":{"start":{"line":6,"column":265,"offset":395},"end":{"line":6,"column":269,"offset":399}}},{"type":"text","value":". Our team thought she could have easily avoided this slip up, if only there was something that acted as a second wall of defense. Thus, Hackers Against Dumb Posts (HADP) was born.","position":{"start":{"line":6,"column":269,"offset":399},"end":{"line":6,"column":449,"offset":579}}}],"position":{"start":{"line":6,"column":1,"offset":131},"end":{"line":6,"column":449,"offset":579}}},{"type":"text","value":"\n"},{"type":"element","tagName":"p","properties":{},"children":[{"type":"text","value":"Our platform consists of an Android keyboard employing a sentiment analysis algorithm and computer vision program. Right before a user posts something, HADP will warn the user on how controversial their post might be based on phrases, topics, and media in the post. We used the following technologies: ","position":{"start":{"line":8,"column":1,"offset":581},"end":{"line":8,"column":303,"offset":883}}},{"type":"raw","value":"<br>","position":{"start":{"line":8,"column":303,"offset":883},"end":{"line":8,"column":307,"offset":887}}},{"type":"text","value":"\n","position":{"start":{"line":8,"column":307,"offset":887},"end":{"line":9,"column":7,"offset":894}}},{"type":"raw","value":"<ul>","position":{"start":{"line":9,"column":7,"offset":894},"end":{"line":9,"column":11,"offset":898}}},{"type":"text","value":"\n","position":{"start":{"line":9,"column":11,"offset":898},"end":{"line":10,"column":7,"offset":905}}},{"type":"raw","value":"<li>","position":{"start":{"line":10,"column":7,"offset":905},"end":{"line":10,"column":11,"offset":909}}},{"type":"text","value":"Flask","position":{"start":{"line":10,"column":11,"offset":909},"end":{"line":10,"column":16,"offset":914}}},{"type":"raw","value":"</li>","position":{"start":{"line":10,"column":16,"offset":914},"end":{"line":10,"column":21,"offset":919}}},{"type":"text","value":"\n","position":{"start":{"line":10,"column":21,"offset":919},"end":{"line":11,"column":7,"offset":926}}},{"type":"raw","value":"<li>","position":{"start":{"line":11,"column":7,"offset":926},"end":{"line":11,"column":11,"offset":930}}},{"type":"text","value":"PyTorch","position":{"start":{"line":11,"column":11,"offset":930},"end":{"line":11,"column":18,"offset":937}}},{"type":"raw","value":"</li>","position":{"start":{"line":11,"column":18,"offset":937},"end":{"line":11,"column":23,"offset":942}}},{"type":"text","value":"\n","position":{"start":{"line":11,"column":23,"offset":942},"end":{"line":12,"column":7,"offset":949}}},{"type":"raw","value":"<li>","position":{"start":{"line":12,"column":7,"offset":949},"end":{"line":12,"column":11,"offset":953}}},{"type":"text","value":"Clarifai API","position":{"start":{"line":12,"column":11,"offset":953},"end":{"line":12,"column":23,"offset":965}}},{"type":"raw","value":"</li>","position":{"start":{"line":12,"column":23,"offset":965},"end":{"line":12,"column":28,"offset":970}}},{"type":"text","value":"\n","position":{"start":{"line":12,"column":28,"offset":970},"end":{"line":13,"column":7,"offset":977}}},{"type":"raw","value":"<li>","position":{"start":{"line":13,"column":7,"offset":977},"end":{"line":13,"column":11,"offset":981}}},{"type":"text","value":"Keras","position":{"start":{"line":13,"column":11,"offset":981},"end":{"line":13,"column":16,"offset":986}}},{"type":"raw","value":"</li>","position":{"start":{"line":13,"column":16,"offset":986},"end":{"line":13,"column":21,"offset":991}}},{"type":"text","value":"\n","position":{"start":{"line":13,"column":21,"offset":991},"end":{"line":14,"column":7,"offset":998}}},{"type":"raw","value":"<li>","position":{"start":{"line":14,"column":7,"offset":998},"end":{"line":14,"column":11,"offset":1002}}},{"type":"text","value":"Pandas","position":{"start":{"line":14,"column":11,"offset":1002},"end":{"line":14,"column":17,"offset":1008}}},{"type":"raw","value":"</li>","position":{"start":{"line":14,"column":17,"offset":1008},"end":{"line":14,"column":22,"offset":1013}}},{"type":"text","value":"\n","position":{"start":{"line":14,"column":22,"offset":1013},"end":{"line":15,"column":7,"offset":1020}}},{"type":"raw","value":"<li>","position":{"start":{"line":15,"column":7,"offset":1020},"end":{"line":15,"column":11,"offset":1024}}},{"type":"text","value":"Tensorflow","position":{"start":{"line":15,"column":11,"offset":1024},"end":{"line":15,"column":21,"offset":1034}}},{"type":"raw","value":"</li>","position":{"start":{"line":15,"column":21,"offset":1034},"end":{"line":15,"column":26,"offset":1039}}},{"type":"text","value":"\n","position":{"start":{"line":15,"column":26,"offset":1039},"end":{"line":16,"column":7,"offset":1046}}},{"type":"raw","value":"</ul>","position":{"start":{"line":16,"column":7,"offset":1046},"end":{"line":16,"column":12,"offset":1051}}}],"position":{"start":{"line":8,"column":1,"offset":581},"end":{"line":16,"column":12,"offset":1051}}},{"type":"text","value":"\n"},{"type":"raw","value":"<br>\n<a href=\"https://github.com/AmirYalamov/Surgeon-Helping-Hand\"><i class=\"fab fa-github fa-2x\"></a> <br>","position":{"start":{"line":18,"column":1,"offset":1053},"end":{"line":19,"column":103,"offset":1160}}}],"position":{"start":{"line":1,"column":1,"offset":0},"end":{"line":20,"column":1,"offset":1161}}}}